Classfile /D:/workspace/space/TestPro/target/classes/com/kyq/test/annotation/classes/ClassUseCase.class
  Last modified 2017-12-15; size 604 bytes
  MD5 checksum 8a8df5d29e8bac4cf0d5ebf2113a0afc
  Compiled from "ClassUseCase.java"
public class com.kyq.test.annotation.classes.ClassUseCase
  minor version: 0
  major version: 52
  flags: ACC_PUBLIC, ACC_SUPER
Constant pool:
   #1 = Methodref          #7.#20         // java/lang/Object."<init>":()V
   #2 = Fieldref           #21.#22        // java/lang/System.out:Ljava/io/PrintStream;
   #3 = String             #12            // test1
   #4 = Methodref          #23.#24        // java/io/PrintStream.println:(Ljava/lang/String;)V
   #5 = String             #13            // test2
   #6 = Class              #25            // com/kyq/test/annotation/classes/ClassUseCase
   #7 = Class              #26            // java/lang/Object
   #8 = Utf8               <init>
   #9 = Utf8               ()V
  #10 = Utf8               Code
  #11 = Utf8               LineNumberTable
  #12 = Utf8               test1
  #13 = Utf8               test2
  #14 = Utf8               SourceFile
  #15 = Utf8               ClassUseCase.java
  #16 = Utf8               RuntimeInvisibleAnnotations
  #17 = Utf8               Lcom/kyq/test/annotation/classes/ClassAnnotationEx;
  #18 = Utf8               value
  #19 = Utf8               ExClass
  #20 = NameAndType        #8:#9          // "<init>":()V
  #21 = Class              #27            // java/lang/System
  #22 = NameAndType        #28:#29        // out:Ljava/io/PrintStream;
  #23 = Class              #30            // java/io/PrintStream
  #24 = NameAndType        #31:#32        // println:(Ljava/lang/String;)V
  #25 = Utf8               com/kyq/test/annotation/classes/ClassUseCase
  #26 = Utf8               java/lang/Object
  #27 = Utf8               java/lang/System
  #28 = Utf8               out
  #29 = Utf8               Ljava/io/PrintStream;
  #30 = Utf8               java/io/PrintStream
  #31 = Utf8               println
  #32 = Utf8               (Ljava/lang/String;)V
{
  public com.kyq.test.annotation.classes.ClassUseCase();
    descriptor: ()V
    flags: ACC_PUBLIC
    Code:
      stack=1, locals=1, args_size=1
         0: aload_0
         1: invokespecial #1                  // Method java/lang/Object."<init>":()V
         4: return
      LineNumberTable:
        line 14: 0

  public void test2();
    descriptor: ()V
    flags: ACC_PUBLIC
    Code:
      stack=2, locals=1, args_size=1
         0: getstatic     #2                  // Field java/lang/System.out:Ljava/io/PrintStream;
         3: ldc           #5                  // String test2
         5: invokevirtual #4                  // Method java/io/PrintStream.println:(Ljava/lang/String;)V
         8: return
      LineNumberTable:
        line 20: 0
        line 21: 8
}
SourceFile: "ClassUseCase.java"
RuntimeInvisibleAnnotations:
  0: #17(#18=s#19)
